auth_tkt/__init__.py
auth_tkt/compat.py
auth_tkt/encrypted.py
auth_tkt/helpers.py
auth_tkt/ticket.py
auth_tkt-0.2.1.dist-info/DESCRIPTION.rst
auth_tkt-0.2.1.dist-info/METADATA
auth_tkt-0.2.1.dist-info/RECORD
auth_tkt-0.2.1.dist-info/WHEEL
auth_tkt-0.2.1.dist-info/metadata.json
auth_tkt-0.2.1.dist-info/top_level.txt
