Metadata-Version: 2.0
Name: auth-tkt
Version: 0.2.1
Summary: Python implementation of mod_auth_tkt cookies
Home-page: http://github.com/yola/auth_tkt
Author: Yola
Author-email: engineers@yola.com
License: MIT (Expat)
Platform: UNKNOWN
Requires-Dist: cryptography (<3.0)
